package_name_matt_gfc/__init__.py
package_name_matt_gfc/converter.py
package_name_matt_gfc-1.0.0.dist-info/LICENSE
package_name_matt_gfc-1.0.0.dist-info/METADATA
package_name_matt_gfc-1.0.0.dist-info/WHEEL
package_name_matt_gfc-1.0.0.dist-info/top_level.txt
package_name_matt_gfc-1.0.0.dist-info/RECORD
